stagedfright.py
primo/__init__.py
primo/data_parser/__init__.py
primo/data_parser/default_data.py
primo/data_parser/input_config.py
primo/data_parser/metric_data.py
primo/data_parser/well_data.py
primo/data_parser/well_data_columns.py
primo/data_parser/tests/__init__.py
primo/data_parser/tests/test_metric_data.py
primo/data_parser/tests/test_well_data.py
primo/data_parser/tests/test_well_data_columns.py
primo/data_parser/tests/test_well_data_common_methods.py
primo/demo/tests/__init__.py
primo/demo/tests/test_demo.py
primo/opt_model/__init__.py
primo/opt_model/model_options.py
primo/opt_model/model_with_clustering.py
primo/opt_model/result_parser.py
primo/opt_model/tests/__init__.py
primo/opt_model/tests/test_model_options.py
primo/opt_model/tests/test_result_parser.py
primo/utils/__init__.py
primo/utils/census_utils.py
primo/utils/clustering_utils.py
primo/utils/config_utils.py
primo/utils/demo_utils.py
primo/utils/domain_validators.py
primo/utils/download_utils.py
primo/utils/elevation_utils.py
primo/utils/estimation_utils.py
primo/utils/geo_utils.py
primo/utils/kpi_utils.py
primo/utils/map_utils.py
primo/utils/multiple_scenario_util.py
primo/utils/opt_utils.py
primo/utils/override_utils.py
primo/utils/proximity_utils.py
primo/utils/raise_exception.py
primo/utils/setup_logger.py
primo/utils/solvers.py
primo/utils/tests/__init__.py
primo/utils/tests/test_census_utils.py
primo/utils/tests/test_clustering_utils.py
primo/utils/tests/test_config_utils.py
primo/utils/tests/test_demo_utils.py
primo/utils/tests/test_domain_validators.py
primo/utils/tests/test_estimation_utils.py
primo/utils/tests/test_geo_utils.py
primo/utils/tests/test_headers.py
primo/utils/tests/test_imports.py
primo/utils/tests/test_kpi_utils.py
primo/utils/tests/test_logger.py
primo/utils/tests/test_map_utils.py
primo/utils/tests/test_opt_utils.py
primo/utils/tests/test_override_utils.py
primo/utils/tests/test_proximity_utils.py
primo/utils/tests/test_secrets.py
primo/utils/tests/test_solvers.py
primo_optimizer-0.2.1.dist-info/LICENSE.md
primo_optimizer-0.2.1.dist-info/METADATA
primo_optimizer-0.2.1.dist-info/WHEEL
primo_optimizer-0.2.1.dist-info/entry_points.txt
primo_optimizer-0.2.1.dist-info/top_level.txt
primo_optimizer-0.2.1.dist-info/RECORD
