Metadata-Version: 2.1
Name: primo-optimizer
Version: 0.2.1
Summary: PRIMO - The P&A Project Optimizer
Author-email: PRIMO team <primo@netl.doe.gov>
Maintainer-email: PRIMO team <primo@netl.doe.gov>
License: License
Project-URL: Documentation, https://primo.readthedocs.io/en/latest/
Project-URL: Download, https://github.com/NEMRI-org/primo-optimizer/releases
Project-URL: Homepage, https://edx.netl.doe.gov/nemri/
Project-URL: Source, https://github.com/NEMRI-org/primo-optimizer
Project-URL: Tracker, https://github.com/NEMRI-org/primo-optimizer/issues
Keywords: PRIMO,MERP,NEMRI,methane emissions,optimization,process modeling,operations research,well plugging
Platform: windows
Platform: linux
Classifier: Development Status :: 3 - Alpha
Classifier: Intended Audience :: End Users/Desktop
Classifier: Intended Audience :: Science/Research
Classifier: License :: OSI Approved :: BSD License
Classifier: Natural Language :: English
Classifier: Operating System :: MacOS
Classifier: Operating System :: Microsoft :: Windows
Classifier: Operating System :: POSIX
Classifier: Operating System :: POSIX :: Linux
Classifier: Operating System :: Unix
Classifier: Programming Language :: Python
Classifier: Programming Language :: Python :: 3
Classifier: Programming Language :: Python :: 3 :: Only
Classifier: Programming Language :: Python :: 3.9
Classifier: Programming Language :: Python :: 3.10
Classifier: Programming Language :: Python :: 3.11
Classifier: Programming Language :: Python :: Implementation :: CPython
Classifier: Topic :: Scientific/Engineering :: Mathematics
Classifier: Topic :: Software Development :: Libraries :: Python Modules
Requires-Python: <3.12,>=3.9
License-File: LICENSE.md
Requires-Dist: appengine-python-standard
Requires-Dist: censusgeocode
Requires-Dist: folium
Requires-Dist: geopandas
Requires-Dist: highspy
Requires-Dist: haversine
Requires-Dist: ipyfilechooser
Requires-Dist: ipyleaflet
Requires-Dist: ipywidgets
Requires-Dist: kneed
Requires-Dist: matplotlib
Requires-Dist: notebook
Requires-Dist: numpy
Requires-Dist: openpyxl
Requires-Dist: pandas
Requires-Dist: pyarrow
Requires-Dist: pyomo
Requires-Dist: pyscipopt
Requires-Dist: python-dotenv
Requires-Dist: scikit-learn
Requires-Dist: rasterio
Requires-Dist: xlsxwriter
Provides-Extra: dev
Requires-Dist: addheader; extra == "dev"
Requires-Dist: black; extra == "dev"
Requires-Dist: isort; extra == "dev"
Requires-Dist: linkify-it-py; extra == "dev"
Requires-Dist: myst-parser; extra == "dev"
Requires-Dist: nbsphinx; extra == "dev"
Requires-Dist: pre-commit; extra == "dev"
Requires-Dist: pylint; extra == "dev"
Requires-Dist: sphinx; extra == "dev"
Requires-Dist: sphinxcontrib-spelling; extra == "dev"
Requires-Dist: sphinx-rtd-theme; extra == "dev"
Provides-Extra: test
Requires-Dist: pytest; extra == "test"
Requires-Dist: pytest-cov; extra == "test"
Requires-Dist: pytest-ipywidgets[notebook]; extra == "test"
Requires-Dist: pytest-playwright; extra == "test"
Provides-Extra: gurobi
Requires-Dist: gurobipy; extra == "gurobi"
